pydumpck/__init__.py
pydumpck/__version__.py
pydumpck/archive_viewer.py
pydumpck/pyinstaller_dump.py
pydumpck/configuration/__init__.py
pydumpck/configuration/res_lock.py
pydumpck/py_common_dump/__init__.py
pydumpck/py_package/__init__.py
pydumpck/py_package/package_description/__init__.py
pydumpck/py_package/package_struct/__init__.py
pydumpck/pyc_checker/__init__.py
pydumpck/pyc_checker/extensions.py
pydumpck/pyc_checker/py_extract.py
pydumpck/pyc_checker/pyz_extract.py
pydumpck/pyc_checker/lib_pycdc/__init__.py
pydumpck/pyc_checker/lib_pycdc/build.py
pydumpck/pyc_checker/lib_pycdc/pycdc.exe
pydumpck/pyc_checker/lib_pycdc/src/pycdc.zip
pydumpck/pyc_checker/lib_uncompyle6/__init__.py
pydumpck/pyc_checker/lib_uncompyle6/requirement_check.py
pydumpck/pyc_checker/pyc/__init__.py
pydumpck/pyc_checker/pyc/headers/__init__.py
pydumpck/pyc_checker/pyc/headers/OpCode/__init__.py
pydumpck/pyc_checker/pyc/headers/OpCode/py3.10.4.py
pydumpck/pyc_checker/pyc/magic_code/__init__.py
pydumpck/utils/__init__.py
pydumpck/utils/banner.py
pydumpck/utils/paths.py
pydumpck/utils/extensions/__init__.py
pydumpck-1.20.1.dist-info/METADATA
pydumpck-1.20.1.dist-info/WHEEL
pydumpck-1.20.1.dist-info/entry_points.txt
pydumpck-1.20.1.dist-info/top_level.txt
pydumpck-1.20.1.dist-info/RECORD
