Metadata-Version: 2.1
Name: pydumpck
Version: 1.20.1
Summary: pydumpck is a multi-threads tool for decompile exe,elf,pyz,pyc packed by python which is base on pycdc and uncompyle6.sometimes its py-file result not exactly right ,maybe could use uncompyle6.
Home-page: https://github.com/serfend/pydumpck
Author: serfend
Author-email: serfend@foxmail.com
License: MIT Licence
Keywords: pydumpck,decomplier,pe,elf,pyc,pyz
Platform: any
Classifier: Development Status :: 5 - Production/Stable
Classifier: Environment :: Web Environment
Classifier: Intended Audience :: Developers
Classifier: License :: OSI Approved :: Apache Software License
Classifier: Natural Language :: English
Classifier: Operating System :: OS Independent
Classifier: Programming Language :: Python
Classifier: Programming Language :: Python :: 3
Classifier: Programming Language :: Python :: 3.7
Classifier: Programming Language :: Python :: 3.8
Classifier: Programming Language :: Python :: 3.9
Classifier: Programming Language :: Python :: 3.10
Classifier: Programming Language :: Python :: 3.11
Classifier: Programming Language :: Python :: 3 :: Only
Classifier: Programming Language :: Python :: Implementation :: CPython
Classifier: Programming Language :: Python :: Implementation :: PyPy
Classifier: Topic :: Software Development :: Libraries
Requires-Python: >=3.7, <4
Requires-Dist: sgtpyutils >=1.19.10
Requires-Dist: pyinstaller >=5.10.1
Requires-Dist: tinyaes
Requires-Dist: uncompyle6 >=3.9.0
Requires-Dist: xdis >=6.0.5
